RTL_trial4/generation/final.v
module alu_selective_io (
    input wire CLK,
    input wire RES,
    input wire STB,
    input wire DATA_VALID_IN,
    input wire [1:0] SEL,
    input wire [7:0] DATA_IN_0,
    input wire [7:0] DATA_IN_1,
    input wire [7:0] DATA_IN_2,
    output wire VALID_0,
    output wire VALID_1,
    output wire [15:0] DATA_OUT_0,
    output wire [15:0] DATA_OUT_1,
    output wire PARITY_0,
    output wire PARITY_1
);

wire gated_valid;
reg [15:0] alu_result;
wire output_channel;

assign gated_valid = (!RES) && STB && DATA_VALID_IN;
assign output_channel = SEL[0];

always @* begin
    case (SEL)
        2'b00: alu_result = DATA_IN_0 * DATA_IN_1;
        2'b01: alu_result = DATA_IN_0 - DATA_IN_1;
        2'b10: alu_result = (DATA_IN_1 == 8'd0) ? 16'h0000 : DATA_IN_0 / DATA_IN_1;
        2'b11: alu_result = (DATA_IN_1 == 8'd0) ? 16'h0000 : DATA_IN_0 % DATA_IN_1;
        default: alu_result = 16'h0000;
    endcase
end

assign VALID_0 = gated_valid && (output_channel == 1'b0);
assign VALID_1 = gated_valid && (output_channel == 1'b1);

assign DATA_OUT_0 = VALID_0 ? alu_result : 16'h0000;
assign DATA_OUT_1 = VALID_1 ? alu_result : 16'h0000;

assign PARITY_0 = VALID_0 ? ^alu_result : 1'b0;
assign PARITY_1 = VALID_1 ? ^alu_result : 1'b0;

endmodule

RTL_trial4/verification/manual_final/manual_final_tb.v
`timescale 1ns/1ps

module manual_final_tb;
    reg CLK;
    reg RES;
    reg STB;
    reg DATA_VALID_IN;
    reg [1:0] SEL;
    reg [7:0] DATA_IN_0;
    reg [7:0] DATA_IN_1;
    reg [7:0] DATA_IN_2;

    wire VALID_0;
    wire VALID_1;
    wire [15:0] DATA_OUT_0;
    wire [15:0] DATA_OUT_1;
    wire PARITY_0;
    wire PARITY_1;

    integer errors;

    alu_selective_io dut (
        .CLK(CLK),
        .RES(RES),
        .STB(STB),
        .DATA_VALID_IN(DATA_VALID_IN),
        .SEL(SEL),
        .DATA_IN_0(DATA_IN_0),
        .DATA_IN_1(DATA_IN_1),
        .DATA_IN_2(DATA_IN_2),
        .VALID_0(VALID_0),
        .VALID_1(VALID_1),
        .DATA_OUT_0(DATA_OUT_0),
        .DATA_OUT_1(DATA_OUT_1),
        .PARITY_0(PARITY_0),
        .PARITY_1(PARITY_1)
    );

    task run_case;
        input [1:0] sel;
        input [7:0] a;
        input [7:0] b;
        input [15:0] expected;
        reg expected_parity;
        reg expected_channel;
        begin
            SEL = sel;
            DATA_IN_0 = a;
            DATA_IN_1 = b;
            DATA_IN_2 = 8'h00;
            STB = 1'b1;
            DATA_VALID_IN = 1'b1;
            RES = 1'b0;
            #5;
            expected_parity = ^expected;
            expected_channel = sel[0];
            if (expected_channel == 1'b0) begin
                if (VALID_0 === 1'b1 && VALID_1 === 1'b0 &&
                    DATA_OUT_0 === expected && DATA_OUT_1 === 16'h0000 &&
                    PARITY_0 === expected_parity && PARITY_1 === 1'b0) begin
                    $display("PASS sel=%b DATA_IN_0=%0d DATA_IN_1=%0d expected=%0d observed=%0d channel=0 parity=%b",
                             sel, a, b, expected, DATA_OUT_0, PARITY_0);
                end else begin
                    errors = errors + 1;
                    $display("FAIL sel=%b DATA_IN_0=%0d DATA_IN_1=%0d expected=%0d observed0=%0d observed1=%0d valid0=%b valid1=%b parity0=%b parity1=%b",
                             sel, a, b, expected, DATA_OUT_0, DATA_OUT_1,
                             VALID_0, VALID_1, PARITY_0, PARITY_1);
                end
            end else begin
                if (VALID_0 === 1'b0 && VALID_1 === 1'b1 &&
                    DATA_OUT_0 === 16'h0000 && DATA_OUT_1 === expected &&
                    PARITY_0 === 1'b0 && PARITY_1 === expected_parity) begin
                    $display("PASS sel=%b DATA_IN_0=%0d DATA_IN_1=%0d expected=%0d observed=%0d channel=1 parity=%b",
                             sel, a, b, expected, DATA_OUT_1, PARITY_1);
                end else begin
                    errors = errors + 1;
                    $display("FAIL sel=%b DATA_IN_0=%0d DATA_IN_1=%0d expected=%0d observed0=%0d observed1=%0d valid0=%b valid1=%b parity0=%b parity1=%b",
                             sel, a, b, expected, DATA_OUT_0, DATA_OUT_1,
                             VALID_0, VALID_1, PARITY_0, PARITY_1);
                end
            end
            #5;
        end
    endtask

    initial begin
        $dumpfile("manual_final.vcd");
        $dumpvars(0, manual_final_tb);

        errors = 0;
        CLK = 1'b0;
        RES = 1'b0;
        STB = 1'b0;
        DATA_VALID_IN = 1'b0;
        SEL = 2'b00;
        DATA_IN_0 = 8'h00;
        DATA_IN_1 = 8'h00;
        DATA_IN_2 = 8'h00;
        #5;

        run_case(2'b00, 8'd3,  8'd10, 16'd30);
        run_case(2'b00, 8'd2,  8'd2,  16'd4);
        run_case(2'b01, 8'd7,  8'd7,  16'd0);
        run_case(2'b01, 8'd4,  8'd3,  16'd1);
        run_case(2'b10, 8'd10, 8'd5,  16'd2);
        run_case(2'b10, 8'd7,  8'd2,  16'd3);
        run_case(2'b11, 8'd10, 8'd2,  16'd0);

        if (errors == 0) $display("OVERALL PASS");
        else $display("OVERALL FAIL errors=%0d", errors);
        $finish;
    end
endmodule

RTL_trial4/verification/manual_final/manual_final.vcd
$date
	Wed Jul 29 15:40:34 2026
$end
$version
	Icarus Verilog
$end
$timescale
	1ps
$end
$scope module manual_final_tb $end
$var wire 1 ! VALID_1 $end
$var wire 1 " VALID_0 $end
$var wire 1 # PARITY_1 $end
$var wire 1 $ PARITY_0 $end
$var wire 16 % DATA_OUT_1 [15:0] $end
$var wire 16 & DATA_OUT_0 [15:0] $end
$var reg 1 ' CLK $end
$var reg 8 ( DATA_IN_0 [7:0] $end
$var reg 8 ) DATA_IN_1 [7:0] $end
$var reg 8 * DATA_IN_2 [7:0] $end
$var reg 1 + DATA_VALID_IN $end
$var reg 1 , RES $end
$var reg 2 - SEL [1:0] $end
$var reg 1 . STB $end
$var integer 32 / errors [31:0] $end
$scope module dut $end
$var wire 1 ' CLK $end
$var wire 8 0 DATA_IN_0 [7:0] $end
$var wire 8 1 DATA_IN_1 [7:0] $end
$var wire 8 2 DATA_IN_2 [7:0] $end
$var wire 1 + DATA_VALID_IN $end
$var wire 1 , RES $end
$var wire 2 3 SEL [1:0] $end
$var wire 1 . STB $end
$var wire 1 " VALID_0 $end
$var wire 1 ! VALID_1 $end
$var wire 1 4 gated_valid $end
$var wire 1 5 output_channel $end
$var wire 1 # PARITY_1 $end
$var wire 1 $ PARITY_0 $end
$var wire 16 6 DATA_OUT_1 [15:0] $end
$var wire 16 7 DATA_OUT_0 [15:0] $end
$var reg 16 8 alu_result [15:0] $end
$upscope $end
$scope task run_case $end
$var reg 8 9 a [7:0] $end
$var reg 8 : b [7:0] $end
$var reg 16 ; expected [15:0] $end
$var reg 1 < expected_channel $end
$var reg 1 = expected_parity $end
$var reg 2 > sel [1:0] $end
$upscope $end
$upscope $end
$enddefinitions $end
$comment Show the parameter values. $end
$dumpall
$end
#0
$dumpvars
bx >
x=
x<
bx ;
bx :
bx 9
b0 8
b0 7
b0 6
05
04
b0 3
b0 2
b0 1
b0 0
b0 /
0.
b0 -
0,
0+
b0 *
b0 )
b0 (
0'
b0 &
b0 %
0$
0#
0"
0!
$end
#5000
b11110 &
b11110 7
1"
14
b11110 8
1+
1.
b1010 )
b1010 1
b11 (
b11 0
b11110 ;
b1010 :
b11 9
b0 >
#10000
0<
0=
#15000
b100 &
b100 7
1$
b100 8
b10 )
b10 1
b10 (
b10 0
b100 ;
b10 :
b10 9
#20000
1=
#25000
1!
0"
b0 &
b0 7
0$
b0 8
15
b111 )
b111 1
b111 (
b111 0
b1 -
b1 3
b0 ;
b111 :
b111 9
b1 >
#30000
1<
0=
#35000
b1 %
b1 6
1#
b1 8
b11 )
b11 1
b100 (
b100 0
b1 ;
b11 :
b100 9
#40000
1=
#45000
0#
b10 &
b10 7
1$
0!
1"
b0 %
b0 6
b10 8
05
b101 )
b101 1
b1010 (
b1010 0
b10 -
b10 3
b10 ;
b101 :
b1010 9
b10 >
#50000
0<
#55000
b11 &
b11 7
0$
b11 8
b10 )
b10 1
b111 (
b111 0
b11 ;
b10 :
b111 9
#60000
0=
#65000
1!
0"
b0 &
b0 7
b0 8
15
b1010 (
b1010 0
b11 -
b11 3
b0 ;
b1010 9
b11 >
#70000
1<
