RTL_trial5/generation/final.v
module alu_selective_io_logic_rel (
    input wire CLK,
    input wire RES,
    input wire STB,
    input wire DATA_VALID_IN,
    input wire [1:0] SEL,
    input wire [7:0] DATA_IN_0,
    input wire [7:0] DATA_IN_1,
    input wire [7:0] DATA_IN_2,
    output wire VALID_0,
    output wire VALID_1,
    output wire [15:0] DATA_OUT_0,
    output wire [15:0] DATA_OUT_1,
    output wire PARITY_0,
    output wire PARITY_1
);

wire gated_valid;
wire output_channel;
wire [2:0] alu_op;
reg [15:0] alu_result;

assign gated_valid = (!RES) && STB && DATA_VALID_IN;
assign output_channel = SEL[0];
assign alu_op = DATA_IN_2[2:0];

always @* begin
    case (alu_op)
        3'b000: alu_result = {8'h00, (DATA_IN_0 & DATA_IN_1)};
        3'b001: alu_result = {8'h00, (DATA_IN_0 | DATA_IN_1)};
        3'b010: alu_result = (DATA_IN_0 >= DATA_IN_1) ? 16'h0001 : 16'h0000;
        3'b011: alu_result = (DATA_IN_0 <= DATA_IN_1) ? 16'h0001 : 16'h0000;
        3'b100: alu_result = (DATA_IN_0 == DATA_IN_1) ? 16'h0001 : 16'h0000;
        3'b101: alu_result = (DATA_IN_0 != DATA_IN_1) ? 16'h0001 : 16'h0000;
        default: alu_result = 16'h0000;
    endcase
end

assign VALID_0 = gated_valid && (output_channel == 1'b0);
assign VALID_1 = gated_valid && (output_channel == 1'b1);

assign DATA_OUT_0 = VALID_0 ? alu_result : 16'h0000;
assign DATA_OUT_1 = VALID_1 ? alu_result : 16'h0000;

assign PARITY_0 = VALID_0 ? ^alu_result : 1'b0;
assign PARITY_1 = VALID_1 ? ^alu_result : 1'b0;

endmodule

RTL_trial5/verification/manual_final/manual_final_tb.v
`timescale 1ns/1ps

module manual_final_tb;
    reg CLK;
    reg RES;
    reg STB;
    reg DATA_VALID_IN;
    reg [1:0] SEL;
    reg [7:0] DATA_IN_0;
    reg [7:0] DATA_IN_1;
    reg [7:0] DATA_IN_2;

    wire VALID_0;
    wire VALID_1;
    wire [15:0] DATA_OUT_0;
    wire [15:0] DATA_OUT_1;
    wire PARITY_0;
    wire PARITY_1;

    integer errors;

    alu_selective_io_logic_rel dut (
        .CLK(CLK),
        .RES(RES),
        .STB(STB),
        .DATA_VALID_IN(DATA_VALID_IN),
        .SEL(SEL),
        .DATA_IN_0(DATA_IN_0),
        .DATA_IN_1(DATA_IN_1),
        .DATA_IN_2(DATA_IN_2),
        .VALID_0(VALID_0),
        .VALID_1(VALID_1),
        .DATA_OUT_0(DATA_OUT_0),
        .DATA_OUT_1(DATA_OUT_1),
        .PARITY_0(PARITY_0),
        .PARITY_1(PARITY_1)
    );

    task run_case;
        input [127:0] label;
        input [1:0] sel;
        input [2:0] op;
        input [7:0] a;
        input [7:0] b;
        input [15:0] expected;
        reg expected_parity;
        reg [15:0] observed;
        begin
            SEL = sel;
            DATA_IN_0 = a;
            DATA_IN_1 = b;
            DATA_IN_2 = {5'b00000, op};
            STB = 1'b1;
            DATA_VALID_IN = 1'b1;
            RES = 1'b0;
            #5;
            expected_parity = ^expected;
            observed = sel[0] ? DATA_OUT_1 : DATA_OUT_0;
            if (((sel[0] == 1'b0) && VALID_0 && !VALID_1 &&
                 DATA_OUT_0 === expected && DATA_OUT_1 === 16'h0000 &&
                 PARITY_0 === expected_parity && PARITY_1 === 1'b0) ||
                ((sel[0] == 1'b1) && !VALID_0 && VALID_1 &&
                 DATA_OUT_0 === 16'h0000 && DATA_OUT_1 === expected &&
                 PARITY_0 === 1'b0 && PARITY_1 === expected_parity)) begin
                $display("PASS %0s DATA_IN_0=%0d DATA_IN_1=%0d expected=%0d observed=%0d channel=%0d parity=%b",
                         label, a, b, expected, observed, sel[0], expected_parity);
            end else begin
                errors = errors + 1;
                $display("FAIL %0s DATA_IN_0=%0d DATA_IN_1=%0d expected=%0d observed0=%0d observed1=%0d valid0=%b valid1=%b parity0=%b parity1=%b",
                         label, a, b, expected, DATA_OUT_0, DATA_OUT_1,
                         VALID_0, VALID_1, PARITY_0, PARITY_1);
            end
            #5;
        end
    endtask

    initial begin
        $dumpfile("manual_final.vcd");
        $dumpvars(0, manual_final_tb);
        errors = 0;
        CLK = 1'b0;
        RES = 1'b0;
        STB = 1'b0;
        DATA_VALID_IN = 1'b0;
        SEL = 2'b00;
        DATA_IN_0 = 8'h00;
        DATA_IN_1 = 8'h00;
        DATA_IN_2 = 8'h00;
        #5;

        run_case("AND", 2'b00, 3'b000, 8'd12, 8'd10, 16'd8);
        run_case("OR",  2'b01, 3'b001, 8'd12, 8'd10, 16'd14);
        run_case("GE",  2'b10, 3'b010, 8'd15, 8'd7,  16'd1);
        run_case("LE",  2'b11, 3'b011, 8'd15, 8'd7,  16'd0);
        run_case("EQ",  2'b10, 3'b100, 8'd4,  8'd9,  16'd0);
        run_case("NE",  2'b11, 3'b101, 8'd4,  8'd9,  16'd1);

        if (errors == 0) $display("OVERALL PASS");
        else $display("OVERALL FAIL errors=%0d", errors);
        $finish;
    end
endmodule

RTL_trial5/verification/manual_final/manual_final.vcd
$date
	Wed Jul 29 18:08:46 2026
$end
$version
	Icarus Verilog
$end
$timescale
	1ps
$end
$scope module manual_final_tb $end
$var wire 1 ! VALID_1 $end
$var wire 1 " VALID_0 $end
$var wire 1 # PARITY_1 $end
$var wire 1 $ PARITY_0 $end
$var wire 16 % DATA_OUT_1 [15:0] $end
$var wire 16 & DATA_OUT_0 [15:0] $end
$var reg 1 ' CLK $end
$var reg 8 ( DATA_IN_0 [7:0] $end
$var reg 8 ) DATA_IN_1 [7:0] $end
$var reg 8 * DATA_IN_2 [7:0] $end
$var reg 1 + DATA_VALID_IN $end
$var reg 1 , RES $end
$var reg 2 - SEL [1:0] $end
$var reg 1 . STB $end
$var integer 32 / errors [31:0] $end
$scope module dut $end
$var wire 1 ' CLK $end
$var wire 8 0 DATA_IN_0 [7:0] $end
$var wire 8 1 DATA_IN_1 [7:0] $end
$var wire 8 2 DATA_IN_2 [7:0] $end
$var wire 1 + DATA_VALID_IN $end
$var wire 1 , RES $end
$var wire 2 3 SEL [1:0] $end
$var wire 1 . STB $end
$var wire 1 " VALID_0 $end
$var wire 1 ! VALID_1 $end
$var wire 1 4 gated_valid $end
$var wire 1 5 output_channel $end
$var wire 3 6 alu_op [2:0] $end
$var wire 1 # PARITY_1 $end
$var wire 1 $ PARITY_0 $end
$var wire 16 7 DATA_OUT_1 [15:0] $end
$var wire 16 8 DATA_OUT_0 [15:0] $end
$var reg 16 9 alu_result [15:0] $end
$upscope $end
$scope task run_case $end
$var reg 8 : a [7:0] $end
$var reg 8 ; b [7:0] $end
$var reg 16 < expected [15:0] $end
$var reg 1 = expected_parity $end
$var reg 128 > label [127:0] $end
$var reg 16 ? observed [15:0] $end
$var reg 3 @ op [2:0] $end
$var reg 2 A sel [1:0] $end
$upscope $end
$upscope $end
$enddefinitions $end
$comment Show the parameter values. $end
$dumpall
$end
#0
$dumpvars
bx A
bx @
bx ?
bx >
x=
bx <
bx ;
bx :
b0 9
b0 8
b0 7
b0 6
05
04
b0 3
b0 2
b0 1
b0 0
b0 /
0.
b0 -
0,
0+
b0 *
b0 )
b0 (
0'
b0 &
b0 %
0$
0#
0"
0!
$end
#5000
b1000 &
b1000 8
1$
1"
14
b1000 9
1+
1.
b1010 )
b1010 1
b1100 (
b1100 0
b1000 <
b1010 ;
b1100 :
b0 @
b0 A
b10000010100111001000100 >
#10000
b1000 ?
1=
#15000
b1110 %
b1110 7
1#
0$
b0 &
b0 8
1!
0"
b1110 9
b1 6
15
b1 *
b1 2
b1 -
b1 3
b1110 <
b1 @
b1 A
b100111101010010 >
#20000
b1110 ?
#25000
b1 &
b1 8
1$
0!
1"
b0 %
b0 7
0#
b10 6
b1 9
05
b10 *
b10 2
b111 )
b111 1
b1111 (
b1111 0
b10 -
b10 3
b1 <
b111 ;
b1111 :
b10 @
b10 A
b100011101000101 >
#30000
b1 ?
#35000
b0 &
b0 8
0$
1!
0"
b0 9
b11 6
15
b11 *
b11 2
b11 -
b11 3
b0 <
b11 @
b11 A
b100110001000101 >
#40000
b0 ?
0=
#45000
0!
1"
b0 %
b0 7
0#
b100 6
b0 9
05
b100 *
b100 2
b1001 )
b1001 1
b100 (
b100 0
b10 -
b10 3
b1001 ;
b100 :
b100 @
b10 A
b100010101010001 >
#55000
b1 %
b1 7
1#
1!
0"
b1 9
b101 6
15
b101 *
b101 2
b11 -
b11 3
b1 <
b101 @
b11 A
b100111001000101 >
#60000
b1 ?
1=
